LICENSE
MANIFEST.in
README.rst
VERSION
setup.py
DriveLink.egg-info/PKG-INFO
DriveLink.egg-info/SOURCES.txt
DriveLink.egg-info/dependency_links.txt
DriveLink.egg-info/top_level.txt
drivelink/__init__.py
drivelink/_diskdict.py
drivelink/_disklink.py
drivelink/_disklist.py
drivelink/_diskmemoize.py
drivelink/_ordereddiskdict.py
drivelink/hash/__init__.py
drivelink/hash/_hasher.py
tests/__init__.py
tests/test_cache.py
tests/test_dict.py
tests/test_hash.py
tests/test_list.py
tests/test_ordereddict.py