Metadata-Version: 1.1
Name: DriveLink
Version: 0.2.3.1
Summary: A set of memory conserving data structures.
Home-page: http://drivelink.rtfd.org/
Author: Chris Dusold
Author-email: DriveLink@ChrisDusold.com
License: The MIT License (MIT)
